README.md
setup.py
src/vdk/plugin/control_cli_name/plugin_entry.py
src/vdk_control_cli_NAME.egg-info/PKG-INFO
src/vdk_control_cli_NAME.egg-info/SOURCES.txt
src/vdk_control_cli_NAME.egg-info/dependency_links.txt
src/vdk_control_cli_NAME.egg-info/entry_points.txt
src/vdk_control_cli_NAME.egg-info/requires.txt
src/vdk_control_cli_NAME.egg-info/top_level.txt